gen_logic/fifo_sync/rtl/fifo_sync.vhd
-- ###############################################################################################
-- # << Synchronous FIFO >> 
-- *********************************************************************************************** 
-- Copyright 2022
-- *********************************************************************************************** 
-- File     : fifo_sync.vhd
-- Author   : David Gussler - davidnguss@gmail.com 
-- Language : VHDL '08
-- History  :  Date      | Version | Comments 
--            --------------------------------
--            04-30-2022 | 1.0     | Initial 
-- *********************************************************************************************** 
-- Description : 
--    Synchronous FIFO module 
-- Generics :
--
--
--
library ieee;
use ieee.std_logic_1164.all;
use ieee.numeric_std.all;
use ieee.math_real.all;


entity fifo_sync is
   generic (
      G_WIDTH        : positive := 32; 
      G_SIZE         : positive := 128; 
      G_ALMOST_FULL  : natural  := 2; 
      G_ALMOST_EMPTY : natural  := 2;
      G_MEM_STYLE    : string  := ""
   );
   port (
      -- Write Port
      i_wr           : in  std_logic; 
      i_dat          : in  std_logic_vector(G_WIDTH-1 downto 0); 
      o_almost_full  : out std_logic; 
      o_full         : out std_logic; 

      -- Read Port
      i_rd           : in  std_logic; 
      o_dat          : out  std_logic_vector(G_WIDTH-1 downto 0); 
      o_almost_empty : out std_logic; 
      o_empty        : out std_logic; 

      i_rst   : in std_logic;
      i_clk   : in std_logic
   );
end entity;

architecture rtl of fifo_sync is
   -- Types 
   type t_fifo  is array (G_SIZE-1 downto 0) of std_logic_vector(G_WIDTH-1 downto 0); 

   -- Constants 
   constant C_ALMOST_FULL_LVL : integer := G_SIZE - G_ALMOST_FULL; 

   -- Wires 
   signal w_full  : std_logic; 
   signal w_empty : std_logic; 

   -- Registers 
   signal r_fifo_cnt : unsigned(G_WIDTH-1 downto 0) := (others=>'0'); 
   signal r_rd_ptr   : unsigned(G_WIDTH-1 downto 0) := (others=>'0'); 
   signal r_wr_ptr   : unsigned(G_WIDTH-1 downto 0) := (others=>'0');   
   signal r_fifo     : t_fifo; 

   -- --------------------------------------------------------------------------------------------
   -- Synthesis Attributes
   -- --------------------------------------------------------------------------------------------  
   -- Viavado 
   attribute ram_style : string;
   attribute ram_style of r_fifo : signal is G_MEM_STYLE;

begin

   -- Assignments
   o_full <= w_full;
   o_empty <= w_empty; 
   o_almost_full  <= '1' when r_fifo_cnt > C_ALMOST_FULL_LVL else '0';
   o_almost_empty <= '1' when r_fifo_cnt < G_ALMOST_EMPTY else '0';
   w_full  <= '1' when r_fifo_cnt = G_SIZE else '0'; 
   w_empty <= '1' when r_fifo_cnt = 0      else '0';

   prc_fifo_sync : process (i_clk)
   begin
      if rising_edge(i_clk) then
         
         -- Determine how full the FIFO is  
         if (i_wr = '1' and w_full = '0') and (i_rd = '0') then 
            r_fifo_cnt <= r_fifo_cnt + 1;
         elsif (i_rd = '1' and w_empty = '0') and (i_wr = '0') then 
            r_fifo_cnt <= r_fifo_cnt - 1;
         end if; 

         -- Write
         if (i_wr = '1' and w_full = '0') then 
            r_fifo(to_integer(r_wr_ptr)) <= i_dat; 
            r_wr_ptr <= r_wr_ptr + 1;
         end if; 

         -- Read 
         if (i_rd = '1' and w_empty = '0') then 
            o_dat <= r_fifo(to_integer(r_rd_ptr)); 
            r_rd_ptr <= r_rd_ptr + 1;
         end if; 

      end if;
   end process;

end architecture;

gen_logic/fifo_sync/sim/cocotb/wave.vcd
$date
  Tue Jul  5 20:47:20 2022
$end
$version
  GHDL v0
$end
$timescale
  1 fs
$end
$scope module standard $end
$upscope $end
$scope module textio $end
$upscope $end
$scope module std_logic_1164 $end
$upscope $end
$scope module numeric_std $end
$upscope $end
$scope module math_real $end
$upscope $end
$scope module fifo_sync $end
$var reg 1 ! i_wr $end
$var reg 32 " i_dat[31:0] $end
$var reg 1 # o_almost_full $end
$var reg 1 $ o_full $end
$var reg 1 % i_rd $end
$var reg 32 & o_dat[31:0] $end
$var reg 1 ' o_almost_empty $end
$var reg 1 ( o_empty $end
$var reg 1 ) i_clk $end
$var reg 1 * w_full $end
$var reg 1 + w_empty $end
$var reg 12 , r_fifo_cnt[11:0] $end
$var reg 11 - r_rd_ptr[10:0] $end
$var reg 11 . r_wr_ptr[10:0] $end
$comment r_fifo is not handled $end
$upscope $end
$enddefinitions $end
#0
1!
b10001010110011001110101001111111 "
0#
0$
0%
bUUUUUUUUUUUUUUUUUUUUUUUUUUUUUUUU &
1'
1(
1)
0*
1+
b000000000000 ,
b00000000000 -
b00000000000 .
#5000000
0)
#10000000
b11100111000111010100001000000001 "
1%
0(
1)
0+
b000000000001 ,
b00000000001 .
#15000000
0)
#20000000
b11001111110011011100101101100111 "
b10001010110011001110101001111111 &
1)
b00000000001 -
b00000000010 .
#25000000
0)
#30000000
b11111100111011011001000000001010 "
0%
b11100111000111010100001000000001 &
1)
b00000000010 -
b00000000011 .
#35000000
0)
#40000000
b10110000011010010000100000010001 "
1)
b000000000010 ,
b00000000100 .
#45000000
0)
#50000000
0'
1)
b000000000011 ,
b00000000101 .
#55000000
0)
#60000000
1)
b000000000100 ,
b00000000110 .
#65000000
0)
#70000000
1)
b000000000101 ,
b00000000111 .
